libdiva/__init__.py
libdiva/__main__.py
libdiva/divafile.py
libdiva/dlt.py
libdiva/farc.py
libdiva-0.1.3.dist-info/licenses/LICENSE
libdiva-0.1.3.dist-info/METADATA
libdiva-0.1.3.dist-info/WHEEL
libdiva-0.1.3.dist-info/entry_points.txt
libdiva-0.1.3.dist-info/top_level.txt
libdiva-0.1.3.dist-info/RECORD
