Metadata-Version: 2.4
Name: libdiva
Version: 0.1.3
Summary: libdiva - a library for manitpulating files specific to the Project Diva series
Author: memoryleak
License-Expression: GPL-3.0-or-later
Project-URL: homepage, https://github.com/Flipleerr/libdiva
Project-URL: repository, https://github.com/Flipleerr/libdiva
Keywords: DLT,library,python,Project Diva
Classifier: Programming Language :: Python :: 3
Classifier: Operating System :: OS Independent
Requires-Python: >=3.8
License-File: LICENSE
Requires-Dist: pycryptodome
Dynamic: license-file
